{"updated":"2026-05-28","election_day":"2026-09-13","weeks_to_go":15,"majority":175,"counts":{"polls":2625,"elections":15,"sims":10000},"latest_poll":{"pollster":"SCB","date":"2026-05-28"},"government":{"right":0.1034,"kingmaker":0.4275,"left":0.4691,"leaders":{"M":"Kristersson","S":"Andersson"},"blocs":{"right":["M","KD","L","SD"],"left":["S","V","MP"],"centre":["C"]}},"parties":[{"code":"S","name":"Socialdemokraterna","color":"#E8112D","bloc":"left","share_mean":0.3333,"share_lo":0.3038,"share_hi":0.3641,"central_seats":122,"seats_mean":123.4,"seats_lo":111,"seats_hi":136,"p_in_riksdag":1.0,"p_below_4pct":0.0},{"code":"SD","name":"Sverigedemokraterna","color":"#C9A227","bloc":"right","share_mean":0.1961,"share_lo":0.1639,"share_hi":0.2305,"central_seats":72,"seats_mean":72.5,"seats_lo":60,"seats_hi":86,"p_in_riksdag":1.0,"p_below_4pct":0.0},{"code":"M","name":"Moderaterna","color":"#52BDEC","bloc":"right","share_mean":0.1761,"share_lo":0.1439,"share_hi":0.2081,"central_seats":64,"seats_mean":65.2,"seats_lo":53,"seats_hi":78,"p_in_riksdag":1.0,"p_below_4pct":0.0},{"code":"V","name":"Vänsterpartiet","color":"#AF0000","bloc":"left","share_mean":0.0763,"share_lo":0.0513,"share_hi":0.1003,"central_seats":28,"seats_mean":27.9,"seats_lo":19,"seats_hi":38,"p_in_riksdag":0.969,"p_below_4pct":0.031},{"code":"MP","name":"Miljöpartiet","color":"#83CF39","bloc":"left","share_mean":0.0636,"share_lo":0.0404,"share_hi":0.0869,"central_seats":23,"seats_mean":22.3,"seats_lo":15,"seats_hi":32,"p_in_riksdag":0.907,"p_below_4pct":0.093},{"code":"C","name":"Centerpartiet","color":"#009933","bloc":"centre","share_mean":0.0588,"share_lo":0.0356,"share_hi":0.0813,"central_seats":22,"seats_mean":19.9,"seats_lo":0,"seats_hi":30,"p_in_riksdag":0.85,"p_below_4pct":0.15},{"code":"KD","name":"Kristdemokraterna","color":"#000077","bloc":"right","share_mean":0.0491,"share_lo":0.0266,"share_hi":0.0708,"central_seats":18,"seats_mean":15.1,"seats_lo":0,"seats_hi":26,"p_in_riksdag":0.716,"p_below_4pct":0.284},{"code":"L","name":"Liberalerna","color":"#006AB3","bloc":"right","share_mean":0.0244,"share_lo":0.0017,"share_hi":0.0445,"central_seats":0,"seats_mean":2.8,"seats_lo":0,"seats_hi":16,"p_in_riksdag":0.161,"p_below_4pct":0.839},{"code":"Övr","name":"Övriga","color":"#9AA0A6","bloc":null,"share_mean":0.0223,"share_lo":0.0,"share_hi":0.0433,"central_seats":0}],"coalitions":[{"name":"Red-green+C (S+V+MP+C)","parties":["S","V","MP","C"],"p_majority":0.897,"mean_seats":193.4,"lo":174,"hi":212},{"name":"Red-green (S+V+MP)","parties":["S","V","MP"],"p_majority":0.469,"mean_seats":173.6,"lo":155,"hi":192},{"name":"Centre-left (S+MP+C)","parties":["S","MP","C"],"p_majority":0.257,"mean_seats":165.5,"lo":148,"hi":183},{"name":"Tidö (M+KD+L+SD)","parties":["M","KD","L","SD"],"p_majority":0.103,"mean_seats":155.6,"lo":137,"hi":175},{"name":"Right ex-SD (M+KD+L+C)","parties":["M","KD","L","C"],"p_majority":0.0,"mean_seats":103.0,"lo":83,"hi":122}],"swing_drama":{"L":{"p_below_4pct":0.8391,"p_right_maj_if_survives":0.26351771286513365,"p_right_maj_if_out":0.07269693719461327},"KD":{"p_below_4pct":0.2845,"p_right_maj_if_survives":0.1371069182389937,"p_right_maj_if_out":0.018629173989455183},"MP":{"p_below_4pct":0.0934,"p_right_maj_if_survives":0.07621883962056034,"p_right_maj_if_out":0.367237687366167},"C":{"p_below_4pct":0.1504,"p_right_maj_if_survives":0.07462335216572505,"p_right_maj_if_out":0.26595744680851063}}}